pkg_95120/__init__.py
pkg_95120/__main__.py
pkg_95120/run.py
pkg_95120-1.1.8.dist-info/licenses/LICENSE
pkg_95120-1.1.8.dist-info/METADATA
pkg_95120-1.1.8.dist-info/WHEEL
pkg_95120-1.1.8.dist-info/entry_points.txt
pkg_95120-1.1.8.dist-info/top_level.txt
pkg_95120-1.1.8.dist-info/RECORD
